pysecuritytxt/__init__.py
pysecuritytxt/api.py
pysecuritytxt/py.typed
pysecuritytxt-1.3.2.dist-info/LICENSE
pysecuritytxt-1.3.2.dist-info/METADATA
pysecuritytxt-1.3.2.dist-info/WHEEL
pysecuritytxt-1.3.2.dist-info/entry_points.txt
pysecuritytxt-1.3.2.dist-info/RECORD
