Metadata-Version: 2.1
Name: pysecuritytxt
Version: 1.3.2
Summary: Python CLI and module for querying security.txt files on domains.
Home-page: https://github.com/Lookyloo/pysecuritytxt
License: BSD-3-Clause
Author: Raphaël Vinot
Author-email: raphael.vinot@circl.lu
Requires-Python: >=3.8,<4.0
Classifier: Development Status :: 5 - Production/Stable
Classifier: Environment :: Console
Classifier: Intended Audience :: Information Technology
Classifier: Intended Audience :: Science/Research
Classifier: Intended Audience :: Telecommunications Industry
Classifier: License :: OSI Approved :: BSD License
Classifier: Operating System :: POSIX :: Linux
Classifier: Programming Language :: Python :: 3
Classifier: Programming Language :: Python :: 3.8
Classifier: Programming Language :: Python :: 3.9
Classifier: Programming Language :: Python :: 3.10
Classifier: Programming Language :: Python :: 3.11
Classifier: Programming Language :: Python :: 3.12
Classifier: Topic :: Internet
Classifier: Topic :: Security
Provides-Extra: docs
Requires-Dist: Sphinx (<7.2) ; (python_version < "3.9") and (extra == "docs")
Requires-Dist: Sphinx (>=7.2,<8.0) ; (python_version >= "3.9") and (extra == "docs")
Requires-Dist: requests (>=2.32.3,<3.0.0)
Project-URL: Documentation, https://pysecuritytxt.readthedocs.io/en/latest/index.html
Project-URL: Repository, https://github.com/Lookyloo/pysecuritytxt
